covidify/README.md
covidify/__init__.py
covidify/cli.py
covidify/config.py
covidify/data_prep.py
covidify/data_visualization.py
covidify/forecast.py
covidify/list_countries.py
covidify/pipeline.sh
covidify/sources/__init__.py
covidify/sources/github.py
covidify/sources/wiki.py
covidify/utils/__init__.py
covidify/utils/utils.py
covidify-1.3.0.dist-info/LICENSE
covidify-1.3.0.dist-info/METADATA
covidify-1.3.0.dist-info/WHEEL
covidify-1.3.0.dist-info/entry_points.txt
covidify-1.3.0.dist-info/top_level.txt
covidify-1.3.0.dist-info/RECORD
