Metadata-Version: 2.1
Name: covidify
Version: 1.3.0
Summary: Stay up to date with corona virus data - Download and generate reports
Home-page: https://github.com/AaronWard/covid-19-analysis
Author: Aaron Ward
Author-email: Aaronward6210@gmail.com
License: MIT
Platform: any
Classifier: Development Status :: 4 - Beta
Classifier: Programming Language :: Python
Requires-Python: >=3.6.*
Requires-Dist: click
Requires-Dist: matplotlib
Requires-Dist: pyarrow
Requires-Dist: pandas
Requires-Dist: docopt
Requires-Dist: GitPython
Requires-Dist: pillow
Requires-Dist: tqdm
Requires-Dist: xlsxwriter
Requires-Dist: numpy
Requires-Dist: pmdarima
Requires-Dist: folium
Requires-Dist: altair
Requires-Dist: seaborn
